[
    {
        "topic": "Rapid Prototyping vs. Rapid Manufacturing: The Shift in Mechanical Design",
        "status": "pending"
    },
    {
        "topic": "The Rise of Metal 3D Printing in Heavy Machinery",
        "status": "pending"
    },
    {
        "topic": "Light-weighting: Topology Optimization in Automotive & Aerospace",
        "status": "pending"
    },
    {
        "topic": "Supply Chain Resilience: Digital Warehousing for Mechanical Spares",
        "status": "pending"
    }
]